firstscrap/__init__.py
firstscrap/conf.py
firstscrap/listhandler.py
firstscrap/pagehandler.py
firstscrap/proxy_list.txt
firstscrap/proxyrefresh.py
firstscrap/useragents.txt
firstscrap/pagehandler/__init__.py
firstscrap/pagehandler/parsers.py
firstscrap/pagehandler/proxy_list.txt
firstscrap/pagehandler/selenium.py
firstscrap/pagehandler/static_parser.py
firstscrap/pagehandler/useragents.txt
firstscrap-0.2.0.dist-info/LICENSE.txt
firstscrap-0.2.0.dist-info/METADATA
firstscrap-0.2.0.dist-info/WHEEL
firstscrap-0.2.0.dist-info/top_level.txt
firstscrap-0.2.0.dist-info/RECORD
