Metadata-Version: 2.1
Name: firstscrap
Version: 0.2.0
Summary: Scraping sites with multithreading, random proxies and user-agents
Home-page: https://github.com/theodor85/first_scrap
Author: Teddy Coder
Author-email: fedor_coder@mail.ru
License: MIT
Platform: UNKNOWN
Classifier: License :: OSI Approved :: MIT License
Classifier: Programming Language :: Python :: 3
Classifier: Programming Language :: Python :: 3.7
Requires-Dist: beautifulsoup4 (==4.9.0)
Requires-Dist: requests (==2.23.0)
Requires-Dist: selenium (==3.141.0)
